hw/rtl/lif_neuron.v
// ============================================================================
// Module: lif_neuron
// Description: Hardware-efficient Leaky Integrate-and-Fire neuron
//              Fixed-point arithmetic: Q8.8 format (8 integer, 8 fractional bits)
// ============================================================================

module lif_neuron #(
    parameter DATA_WIDTH = 16,
    parameter LEAK_SHIFT = 3  // Leak factor = 1 - 2^(-LEAK_SHIFT) = 0.875
)(
    input  wire                    clk,
    input  wire                    rst_n,
    input  wire                    spike_in,       // Input spike (1 bit)
    input  wire signed [DATA_WIDTH-1:0] weight,    // Synaptic weight (Q8.8)
    input  wire signed [DATA_WIDTH-1:0] threshold, // Firing threshold (Q8.8)
    output reg                     spike_out,      // Output spike (1 bit)
    output wire signed [DATA_WIDTH-1:0] membrane_potential  // Debug output
);

    // Membrane potential register (Q8.8 format)
    reg signed [DATA_WIDTH-1:0] V_mem;
    
    // Leak operation: V_leaked = V_mem - (V_mem >> LEAK_SHIFT)
    // This implements V_mem * (1 - 2^(-LEAK_SHIFT))
    wire signed [DATA_WIDTH-1:0] V_leaked;
    
    // Input current: I = spike_in ? weight : 0
    wire signed [DATA_WIDTH-1:0] I_in;
    
    // Leak calculation (arithmetic right shift preserves sign)
    assign V_leaked = V_mem - (V_mem >>> LEAK_SHIFT);
    
    // Input current
    assign I_in = spike_in ? weight : 16'sd0;
    
    // Membrane potential update: V[t] = V_leaked + I_in
    always @(posedge clk or negedge rst_n) begin
        if (!rst_n) begin
            V_mem <= 16'sd0;
        end else if (spike_out) begin
            // Reset membrane potential after spike (hard reset)
            V_mem <= 16'sd0;
        end else begin
            V_mem <= V_leaked + I_in;
        end
    end
    
    // Spike generation: fire if V_mem >= threshold
    always @(posedge clk or negedge rst_n) begin
        if (!rst_n) begin
            spike_out <= 1'b0;
        end else begin
            spike_out <= (V_mem >= threshold) ? 1'b1 : 1'b0;
        end
    end
    
    // Debug output
    assign membrane_potential = V_mem;

endmodule

hw/tb/tb_lif_neuron.v
`timescale 1ns/1ps

module tb_lif_neuron;
    
    // Parameters
    localparam DATA_WIDTH = 16;
    localparam LEAK_SHIFT = 3;
    localparam CLK_PERIOD = 10; // 10ns, 100MHz clock
    
    // Signals
    reg clk;
    reg rst_n;
    reg spike_in;
    reg signed [DATA_WIDTH-1:0] weight;
    reg signed [DATA_WIDTH-1:0] threshold;
    wire spike_out;
    wire signed [DATA_WIDTH-1:0] membrane_potential;
    
    // Instantiate DUT (Device Under Test)
    lif_neuron #(
        .DATA_WIDTH(DATA_WIDTH),
        .LEAK_SHIFT(LEAK_SHIFT)
    ) dut (
        .clk(clk),
        .rst_n(rst_n),
        .spike_in(spike_in),
        .weight(weight),
        .threshold(threshold),
        .spike_out(spike_out),
        .membrane_potential(membrane_potential)
    );
    
    // Clock generation
    initial begin
        clk = 0;
        forever #(CLK_PERIOD/2) clk = ~clk;
    end
    
    // Test stimulus
    initial begin
        // Initialize
        rst_n = 0;
        spike_in = 0;
        weight = 16'sh0100;      // 1.0 in Q8.8 format
        threshold = 16'sh0080;   // 0.5 in Q8.8 format
        
        // Reset
        #100;
        rst_n = 1;
        #50;
        
        // Test 1: Single spike input
        $display("Test 1: Single spike input");
        spike_in = 1;
        #20;
        spike_in = 0;
        #100;
        $display("  Membrane potential after spike: %d", membrane_potential);
        
        // Test 2: Multiple spikes (should accumulate)
        $display("\nTest 2: Multiple spike inputs");
        repeat(5) begin
            spike_in = 1;
            #20;
            spike_in = 0;
            #20;
        end
        #100;
        $display("  Membrane potential after 5 spikes: %d", membrane_potential);
        
        // Test 3: Spike firing (membrane should exceed threshold)
        $display("\nTest 3: Spike firing");
        repeat(10) begin
            spike_in = 1;
            #20;
            spike_in = 0;
            #20;
        end
        #100;
        $display("  Spike output observed: %b", spike_out);
        $display("  Membrane potential after firing: %d", membrane_potential);
        
        // Test 4: Leak behavior (no input, membrane should decay)
        $display("\nTest 4: Leak behavior");
        spike_in = 0;
        #200;
        $display("  Membrane potential after leak: %d", membrane_potential);
        
        $display("\n✅ All tests completed");
        $finish;
    end
    
    // Monitor outputs
    initial begin
        $monitor("Time=%0t | rst_n=%b | spike_in=%b | V_mem=%d | spike_out=%b",
                 $time, rst_n, spike_in, membrane_potential, spike_out);
    end
    
    // Waveform dump
    initial begin
        $dumpfile("lif_neuron.vcd");
        $dumpvars(0, tb_lif_neuron);
    end

endmodule

hw/sim/lif_neuron.vcd
$date
	Wed Sep 16 01:10:08 2026
$end
$version
	Icarus Verilog
$end
$timescale
	1ps
$end
$scope module tb_lif_neuron $end
$var wire 1 ! spike_out $end
$var wire 16 " membrane_potential [15:0] $end
$var reg 1 # clk $end
$var reg 1 $ rst_n $end
$var reg 1 % spike_in $end
$var reg 16 & threshold [15:0] $end
$var reg 16 ' weight [15:0] $end
$scope module dut $end
$var wire 1 # clk $end
$var wire 16 ( membrane_potential [15:0] $end
$var wire 1 $ rst_n $end
$var wire 1 % spike_in $end
$var wire 16 ) threshold [15:0] $end
$var wire 16 * weight [15:0] $end
$var wire 16 + V_leaked [15:0] $end
$var wire 16 , I_in [15:0] $end
$var reg 16 - V_mem [15:0] $end
$var reg 1 ! spike_out $end
$upscope $end
$upscope $end
$enddefinitions $end
#0
$dumpvars
b0 -
b0 ,
b0 +
b100000000 *
b10000000 )
b0 (
b100000000 '
b10000000 &
0%
0$
0#
b0 "
0!
$end
#5000
1#
#10000
0#
#15000
1#
#20000
0#
#25000
1#
#30000
0#
#35000
1#
#40000
0#
#45000
1#
#50000
0#
#55000
1#
#60000
0#
#65000
1#
#70000
0#
#75000
1#
#80000
0#
#85000
1#
#90000
0#
#95000
1#
#100000
0#
1$
#105000
1#
#110000
0#
#115000
1#
#120000
0#
#125000
1#
#130000
0#
#135000
1#
#140000
0#
#145000
1#
#150000
b100000000 ,
0#
1%
#155000
b11100000 +
b100000000 "
b100000000 (
b100000000 -
1#
#160000
0#
#165000
1!
b110100100 +
b111100000 "
b111100000 (
b111100000 -
1#
#170000
b0 ,
0#
0%
#175000
b0 +
b0 "
b0 (
b0 -
1#
#180000
0#
#185000
0!
1#
#190000
0#
#195000
1#
#200000
0#
#205000
1#
#210000
0#
#215000
1#
#220000
0#
#225000
1#
#230000
0#
#235000
1#
#240000
0#
#245000
1#
#250000
0#
#255000
1#
#260000
0#
#265000
1#
#270000
b100000000 ,
0#
1%
#275000
b11100000 +
b100000000 "
b100000000 (
b100000000 -
1#
#280000
0#
#285000
1!
b110100100 +
b111100000 "
b111100000 (
b111100000 -
1#
#290000
b0 ,
0#
0%
#295000
b0 +
b0 "
b0 (
b0 -
1#
#300000
0#
#305000
0!
1#
#310000
b100000000 ,
0#
1%
#315000
b11100000 +
b100000000 "
b100000000 (
b100000000 -
1#
#320000
0#
#325000
1!
b110100100 +
b111100000 "
b111100000 (
b111100000 -
1#
#330000
b0 ,
0#
0%
#335000
b0 +
b0 "
b0 (
b0 -
1#
#340000
0#
#345000
0!
1#
#350000
b100000000 ,
0#
1%
#355000
b11100000 +
b100000000 "
b100000000 (
b100000000 -
1#
#360000
0#
#365000
1!
b110100100 +
b111100000 "
b111100000 (
b111100000 -
1#
#370000
b0 ,
0#
0%
#375000
b0 +
b0 "
b0 (
b0 -
1#
#380000
0#
#385000
0!
1#
#390000
b100000000 ,
0#
1%
#395000
b11100000 +
b100000000 "
b100000000 (
b100000000 -
1#
#400000
0#
#405000
1!
b110100100 +
b111100000 "
b111100000 (
b111100000 -
1#
#410000
b0 ,
0#
0%
#415000
b0 +
b0 "
b0 (
b0 -
1#
#420000
0#
#425000
0!
1#
#430000
b100000000 ,
0#
1%
#435000
b11100000 +
b100000000 "
b100000000 (
b100000000 -
1#
#440000
0#
#445000
1!
b110100100 +
b111100000 "
b111100000 (
b111100000 -
1#
#450000
b0 ,
0#
0%
#455000
b0 +
b0 "
b0 (
b0 -
1#
#460000
0#
#465000
0!
1#
#470000
0#
#475000
1#
#480000
0#
#485000
1#
#490000
0#
#495000
1#
#500000
0#
#505000
1#
#510000
0#
#515000
1#
#520000
0#
#525000
1#
#530000
0#
#535000
1#
#540000
0#
#545000
1#
#550000
0#
#555000
1#
#560000
0#
#565000
1#
#570000
b100000000 ,
0#
1%
#575000
b11100000 +
b100000000 "
b100000000 (
b100000000 -
1#
#580000
0#
#585000
1!
b110100100 +
b111100000 "
b111100000 (
b111100000 -
1#
#590000
b0 ,
0#
0%
#595000
b0 +
b0 "
b0 (
b0 -
1#
#600000
0#
#605000
0!
1#
#610000
b100000000 ,
0#
1%
#615000
b11100000 +
b100000000 "
b100000000 (
b100000000 -
1#
#620000
0#
#625000
1!
b110100100 +
b111100000 "
b111100000 (
b111100000 -
1#
#630000
b0 ,
0#
0%
#635000
b0 +
b0 "
b0 (
b0 -
1#
#640000
0#
#645000
0!
1#
#650000
b100000000 ,
0#
1%
#655000
b11100000 +
b100000000 "
b100000000 (
b100000000 -
1#
#660000
0#
#665000
1!
b110100100 +
b111100000 "
b111100000 (
b111100000 -
1#
#670000
b0 ,
0#
0%
#675000
b0 +
b0 "
b0 (
b0 -
1#
#680000
0#
#685000
0!
1#
#690000
b100000000 ,
0#
1%
#695000
b11100000 +
b100000000 "
b100000000 (
b100000000 -
1#
#700000
0#
#705000
1!
b110100100 +
b111100000 "
b111100000 (
b111100000 -
1#
#710000
b0 ,
0#
0%
#715000
b0 +
b0 "
b0 (
b0 -
1#
#720000
0#
#725000
0!
1#
#730000
b100000000 ,
0#
1%
#735000
b11100000 +
b100000000 "
b100000000 (
b100000000 -
1#
#740000
0#
#745000
1!
b110100100 +
b111100000 "
b111100000 (
b111100000 -
1#
#750000
b0 ,
0#
0%
#755000
b0 +
b0 "
b0 (
b0 -
1#
#760000
0#
#765000
0!
1#
#770000
b100000000 ,
0#
1%
#775000
b11100000 +
b100000000 "
b100000000 (
b100000000 -
1#
#780000
0#
#785000
1!
b110100100 +
b111100000 "
b111100000 (
b111100000 -
1#
#790000
b0 ,
0#
0%
#795000
b0 +
b0 "
b0 (
b0 -
1#
#800000
0#
#805000
0!
1#
#810000
b100000000 ,
0#
1%
#815000
b11100000 +
b100000000 "
b100000000 (
b100000000 -
1#
#820000
0#
#825000
1!
b110100100 +
b111100000 "
b111100000 (
b111100000 -
1#
#830000
b0 ,
0#
0%
#835000
b0 +
b0 "
b0 (
b0 -
1#
#840000
0#
#845000
0!
1#
#850000
b100000000 ,
0#
1%
#855000
b11100000 +
b100000000 "
b100000000 (
b100000000 -
1#
#860000
0#
#865000
1!
b110100100 +
b111100000 "
b111100000 (
b111100000 -
1#
#870000
b0 ,
0#
0%
#875000
b0 +
b0 "
b0 (
b0 -
1#
#880000
0#
#885000
0!
1#
#890000
b100000000 ,
0#
1%
#895000
b11100000 +
b100000000 "
b100000000 (
b100000000 -
1#
#900000
0#
#905000
1!
b110100100 +
b111100000 "
b111100000 (
b111100000 -
1#
#910000
b0 ,
0#
0%
#915000
b0 +
b0 "
b0 (
b0 -
1#
#920000
0#
#925000
0!
1#
#930000
b100000000 ,
0#
1%
#935000
b11100000 +
b100000000 "
b100000000 (
b100000000 -
1#
#940000
0#
#945000
1!
b110100100 +
b111100000 "
b111100000 (
b111100000 -
1#
#950000
b0 ,
0#
0%
#955000
b0 +
b0 "
b0 (
b0 -
1#
#960000
0#
#965000
0!
1#
